exn_report_sdk-0.1.12.dist-info/licenses/LICENSE
exn_salon_report_sdk/__init__.py
exn_salon_report_sdk/client.py
exn_salon_report_sdk/config.py
exn_salon_report_sdk/exceptions.py
exn_salon_report_sdk/utils.py
exn_report_sdk-0.1.12.dist-info/METADATA
exn_report_sdk-0.1.12.dist-info/WHEEL
exn_report_sdk-0.1.12.dist-info/top_level.txt
exn_report_sdk-0.1.12.dist-info/RECORD
