Metadata-Version: 2.4
Name: exn-report-sdk
Version: 0.1.12
Summary: Python SDK for Report Service.
Author-email: Exnodes <ryan@exnodes.vn>
License: MIT
Project-URL: Homepage, https://github.com/Salonbookly/Report-SDK
Keywords: report,sdk,api
Classifier: Programming Language :: Python :: 3
Classifier: License :: OSI Approved :: MIT License
Classifier: Operating System :: OS Independent
Requires-Python: >=3.9
License-File: LICENSE
Requires-Dist: requests>=2.26.0
Dynamic: license-file
